kj_depviz/__init__.py
kj_depviz/dep.png
kj_depviz/main.py
kj_depviz-0.1.0.dist-info/METADATA
kj_depviz-0.1.0.dist-info/WHEEL
kj_depviz-0.1.0.dist-info/entry_points.txt
kj_depviz-0.1.0.dist-info/top_level.txt
kj_depviz-0.1.0.dist-info/RECORD
