Metadata-Version: 2.4
Name: kj-depviz
Version: 0.1.0
Summary: A visualizer for Python packages using UV dependencies.
Author-email: Karan Jain <karanrpjain@gmail.com>
Classifier: Programming Language :: Python :: 3
Classifier: License :: OSI Approved :: MIT License
Classifier: Operating System :: OS Independent
Requires-Python: >=3.9
Requires-Dist: fastapi
Requires-Dist: uvicorn
Requires-Dist: pydantic
Requires-Dist: google-genai
Requires-Dist: tomli; python_version < "3.11"
